mkdocs_pdf_viewer/__init__.py
mkdocs_pdf_viewer/plugin.py
mkdocs_pdf_viewer-0.1.0.dist-info/METADATA
mkdocs_pdf_viewer-0.1.0.dist-info/WHEEL
mkdocs_pdf_viewer-0.1.0.dist-info/entry_points.txt
mkdocs_pdf_viewer-0.1.0.dist-info/top_level.txt
mkdocs_pdf_viewer-0.1.0.dist-info/RECORD
