Metadata-Version: 2.1
Name: mkdocs-pdf-viewer
Version: 0.1.0
Summary: A MkDocs plugin to open PDFs in a modal.
Home-page: https://github.com/niclasheinz/mkdocs-pdf-viewer
Author: Niclas Heinz
Author-email: your.email@example.com
Requires-Dist: mkdocs-material>=9.0.0
